ai/backend/accelerator/cuda/__init__.py
ai/backend/accelerator/cuda/nvidia.py
ai/backend/accelerator/cuda/plugin.py
backend.ai_accelerator_cuda-2.0.1.dist-info/LICENSE
backend.ai_accelerator_cuda-2.0.1.dist-info/METADATA
backend.ai_accelerator_cuda-2.0.1.dist-info/WHEEL
backend.ai_accelerator_cuda-2.0.1.dist-info/entry_points.txt
backend.ai_accelerator_cuda-2.0.1.dist-info/top_level.txt
backend.ai_accelerator_cuda-2.0.1.dist-info/RECORD
