Metadata-Version: 2.1
Name: backend.ai-accelerator-cuda
Version: 2.0.1
Summary: Backend.AI Accelerator Plugin for CUDA
Home-page: https://backend.ai
Author: Lablup Inc.
Author-email: joongi@lablup.com
License: LGPLv3
Project-URL: Documentation, https://docs.backend.ai
Platform: UNKNOWN
Classifier: Development Status :: 5 - Production/Stable
Classifier: License :: OSI Approved :: GNU Lesser General Public License v3 or later (LGPLv3+)
Classifier: Intended Audience :: Developers
Classifier: Programming Language :: Python
Classifier: Programming Language :: Python :: 3
Classifier: Programming Language :: Python :: 3.6
Classifier: Programming Language :: Python :: 3.7
Classifier: Programming Language :: Python :: 3.8
Classifier: Operating System :: POSIX
Classifier: Operating System :: MacOS :: MacOS X
Classifier: Environment :: No Input/Output (Daemon)
Classifier: Topic :: Scientific/Engineering
Classifier: Topic :: Software Development
Requires-Python: >=3.6
Requires-Dist: aiohttp (>=3.6.2)
Requires-Dist: attrs (>=19.3)
Provides-Extra: build
Requires-Dist: wheel (>=0.33.6) ; extra == 'build'
Requires-Dist: twine (>=1.14.0) ; extra == 'build'
Provides-Extra: ci
Provides-Extra: dev
Requires-Dist: pytest-sugar ; extra == 'dev'
Provides-Extra: test
Requires-Dist: pytest (>=6.1.2) ; extra == 'test'
Requires-Dist: pytest-asyncio (>=0.14.0) ; extra == 'test'
Requires-Dist: pytest-cov ; extra == 'test'
Requires-Dist: pytest-mock ; extra == 'test'
Requires-Dist: asynctest ; extra == 'test'
Requires-Dist: flake8 (>=3.8.4) ; extra == 'test'
Requires-Dist: mypy (>=0.790) ; extra == 'test'
Requires-Dist: codecov ; extra == 'test'
